cloudsync_onedrive.py
cloudsync_onedrive-3.2.1.dist-info/entry_points.txt
cloudsync_onedrive-3.2.1.dist-info/WHEEL
cloudsync_onedrive-3.2.1.dist-info/METADATA
cloudsync_onedrive-3.2.1.dist-info/RECORD
