Metadata-Version: 2.1
Name: cloudsync_onedrive
Version: 3.2.1
Summary: Onedrive provider
Home-page: https://github.com/atakamallc/cloudsync-onedrive
Author: Atakama, LLC
Author-email: dev-support@atakama.com
Requires-Python: >=3.6
Classifier: Intended Audience :: Developers
Classifier: License :: OSI Approved :: GNU Lesser General Public License v3 or later (LGPLv3+)
Classifier: Programming Language :: Python
Classifier: Topic :: Software Development :: Libraries :: Python Modules
Requires-Dist: cloudsync>=3.3.1
Requires-Dist: quickxorhash
Requires-Dist: dataclasses; python_version < '3.7'
Requires-Dist: requests
